{"pageProps":{"questions":[{"id":"oeaKgBgAG3icxfzDoebQ","question_images":[],"answers_community":[],"question_text":"What is the minimum level of SNMP that provides encryption?","topic":"2","isMC":true,"choices":{"C":"SNMPv3 noAuthNoPriv","A":"SNMPv3 authPriv","B":"SNMPv3 authNoPriv","D":"SNMPv2 noAuthNoPriv A"},"unix_timestamp":1581684540,"answer":"Explanation","exam_id":284,"url":"https://www.examtopics.com/discussions/cisco/view/14124-exam-200-105-topic-2-question-69-discussion/","timestamp":"2020-02-14 13:49:00","answer_description":"","answer_ET":"Explanation","answer_images":[],"discussion":[{"poster":"elias1986","timestamp":"1581684540.0","content":"answer is A","comment_id":"50475","upvote_count":"2"}],"question_id":161},{"id":"nLZe7y8dhDyGl9EFzwJw","unix_timestamp":1581272700,"answer":"Explanation","exam_id":284,"answer_description":"","choices":{"D":"It runs normally and flags all possible ACE entries as invalid. A","B":"It runs normally and reports that traffic for all possible protocol matches is denied.","C":"It fails to execute the path trace.","A":"It runs normally and reports all possible ACE matches for the protocol field."},"question_images":[],"answer_ET":"Explanation","discussion":[{"poster":"acmoreno","upvote_count":"1","timestamp":"1581272700.0","comment_id":"48415","content":"letter A"}],"timestamp":"2020-02-09 19:25:00","isMC":true,"question_id":162,"answer_images":[],"question_text":"You attempt to execute the APIC-EM ACL path trace feature without specifying the protocol. How does the ACL path trace respond?","url":"https://www.examtopics.com/discussions/cisco/view/13676-exam-200-105-topic-2-question-73-discussion/","answers_community":[],"topic":"2"},{"id":"66hROrtyu1BFwvhr0OIB","discussion":[{"content":"A & E are the correct answers","upvote_count":"1","poster":"SmaCisco","comment_id":"53345","timestamp":"1582274220.0"}],"url":"https://www.examtopics.com/discussions/cisco/view/14605-exam-200-105-topic-2-question-77-discussion/","unix_timestamp":1582274220,"question_images":[],"question_text":"Which two statements identify differences between single-homed and dual-homed WAN topologies? (Choose two.)","exam_id":284,"answer":"Explanation","isMC":true,"topic":"2","answer_ET":"Explanation","answer_description":"","timestamp":"2020-02-21 09:37:00","question_id":163,"answers_community":[],"answer_images":[],"choices":{"C":"Single-homed topologies are more costly to an enterprise than dual-homed topologies","E":"Single-homed topologies are more appropriate for small-business networks than dual-homed topologies AE","B":"Only dual-homed connections require dynamic routing to the ISP","D":"Only dual-homed connections are connected to the same ISP","A":"Dual-homed topologies provide greater redundancy than single-homed topologies"}},{"id":"jeRodN59nb1NzblVzcZj","question_id":164,"choices":{"C":"link-state","D":"distance-vector C","A":"path-vector","B":"hybrid routing"},"isMC":true,"unix_timestamp":1582274340,"question_text":"Which type of routing protocol relies on the shortest path tree?","answers_community":[],"question_images":[],"exam_id":284,"url":"https://www.examtopics.com/discussions/cisco/view/14606-exam-200-105-topic-2-question-80-discussion/","answer_description":"","timestamp":"2020-02-21 09:39:00","discussion":[{"timestamp":"1582274340.0","upvote_count":"1","comment_id":"53346","poster":"SmaCisco","content":"C Link State"}],"answer_ET":"Explanation","topic":"2","answer_images":[],"answer":"Explanation"},{"id":"dUePfKwd2C5SiHho67OE","timestamp":"2020-01-16 23:40:00","question_images":[],"choices":{"C":"limiting debug output","A":"identifying QoS traffic for marking","D":"noncontiguous port filtering","E":"deleting entries DE","B":"filtering traffic on VTY lines"},"topic":"2","answer_description":"Reference:\nhttps://www.cisco.com/c/en/us/td/docs/ios-xml/ios/sec_data_acl/configuration/xe-3s/sec-data-acl-xe-3s-book/sec-acl-named.pdf","answer_ET":"Explanation","unix_timestamp":1579214400,"question_id":165,"url":"https://www.examtopics.com/discussions/cisco/view/12183-exam-200-105-topic-2-question-82-discussion/","question_text":"Which two features are supported only in named access lists? (Choose two.)","discussion":[{"timestamp":"1579214400.0","poster":"EDwdo","comment_id":"39911","content":"The answers are B&D","comments":[{"comment_id":"40489","timestamp":"1579387980.0","upvote_count":"2","content":"It's D & E.\n\nIt's not B because both named and numbered access lists can be applied to VTY lines.","poster":"JTA2020"}],"upvote_count":"1"}],"exam_id":284,"answers_community":[],"isMC":true,"answer_images":[],"answer":"Explanation"}],"exam":{"lastUpdated":"12 Apr 2025","name":"200-105","isImplemented":true,"isBeta":false,"provider":"Cisco","isMCOnly":false,"id":284,"numberOfQuestions":168},"currentPage":33},"__N_SSP":true}