{"pageProps":{"questions":[{"id":"VvFnl6TJZiUT25nQbPHg","answer_ET":"A","answer":"A","answers_community":[],"timestamp":"2019-12-20 04:22:00","question_id":116,"question_images":[],"choices":{"B":"Import from CUCM via AXL","D":"Manual creation","C":"Import from LDAP","A":"Bulk administration"},"url":"https://www.examtopics.com/discussions/cisco/view/10701-exam-210-060-topic-2-question-7-discussion/","answer_images":[],"isMC":true,"answer_description":"","exam_id":292,"unix_timestamp":1576812120,"topic":"2","discussion":[{"upvote_count":"1","poster":"MarkusW","timestamp":"1580903700.0","comment_id":"46871","content":"C. Import from LDAP\nImport the relevant information from LDAP but use Unity-related information updateble in Unity."},{"content":"Should be D","poster":"dean0402","comment_id":"31209","timestamp":"1576812120.0","upvote_count":"1"}],"question_text":"An engineer must ensure that user data is maintained in lightweight directory access protocol and copied to Cisco Unity Connection, but Cisco Unity Connection- specific data is locally maintained in the Cisco Unity Connection database. Which user creation option accomplishes this task?"},{"id":"IYi9pbthaW386C7LiEIf","answer_images":[],"choices":{"C":"Cisco Mobility Remote Destination","A":"Cisco Extension Mobility","B":"Cisco TMS","E":"Cisco Mobile and Remote Access","D":"Cisco Unified RTMT"},"answer_description":"","discussion":[{"content":"E is the correct answer","poster":"Bianco","comment_id":"80106","timestamp":"1587950220.0","upvote_count":"1"},{"upvote_count":"2","content":"Definitely MRA","timestamp":"1564424160.0","comment_id":"5277","poster":"trikatsu"},{"upvote_count":"3","content":"The answer should be Cisco Mobile and Remote Access.","comment_id":"3485","timestamp":"1562162940.0","poster":"daytonadave2011"}],"exam_id":292,"question_text":"Which component allows Cisco Jabber to communicate with clients who are outside the corporate network?","timestamp":"2019-07-03 16:09:00","answer":"A","question_id":117,"isMC":true,"topic":"2","answers_community":[],"unix_timestamp":1562162940,"answer_ET":"A","url":"https://www.examtopics.com/discussions/cisco/view/2158-exam-210-060-topic-2-question-8-discussion/","question_images":[]},{"id":"G83tDpy1cemjOoM9LCNx","url":"https://www.examtopics.com/discussions/cisco/view/1109-exam-210-060-topic-2-question-9-discussion/","timestamp":"2019-05-01 05:47:00","unix_timestamp":1556682420,"question_id":118,"topic":"2","isMC":true,"question_images":[],"answer":"AB","answer_ET":"AB","question_text":"What are three ways for an administrator to create users in Cisco Unity Connection? (Choose three.)","answer_description":"","answers_community":[],"exam_id":292,"choices":{"E":"Use manual creation","C":"Import from a Microsoft Word document","A":"Use the Bulk Administration Tool","B":"Import from Cisco Unified Communications Manager Express","F":"Import from a Microsoft Outlook contacts list G. import from LDAP","D":"Import from an Adobe PDF document"},"discussion":[{"timestamp":"1580723040.0","comment_id":"46086","poster":"MarkusW","upvote_count":"2","content":"A. Use the Bulk Administration Tool\nE. Use manual creation\nG. import from LDAP"},{"content":"Concur, AEG","timestamp":"1576812180.0","poster":"dean0402","upvote_count":"4","comment_id":"31210"},{"timestamp":"1571993700.0","upvote_count":"1","poster":"twill","content":"I think you mean A, B, & E. There is no G.","comment_id":"17343"},{"content":"should be A,E,G","timestamp":"1563631200.0","comment_id":"4500","poster":"kikx3","upvote_count":"4"},{"upvote_count":"2","poster":"Devon","comment_id":"1483","content":"Use manual creation","timestamp":"1556682420.0"}],"answer_images":[]}],"exam":{"provider":"Cisco","numberOfQuestions":118,"isImplemented":true,"id":292,"isBeta":false,"name":"210-060","lastUpdated":"12 Apr 2025","isMCOnly":false},"currentPage":24},"__N_SSP":true}