{"pageProps":{"questions":[{"id":"i9UAOglxWVh3N5RsJEAk","question_images":[],"answer":"A","timestamp":"2020-06-13 10:40:00","answer_ET":"A","choices":{"A":"error | table action, src, dest","B":"error | tabular action, src, dest","C":"error | stats table action, src, dest","D":"error | table column=action column=src column=dest"},"topic":"1","answer_description":"","question_text":"Which search will return only events containing the word `error` and display the results as a table that includes the fields named action, src, and dest?","url":"https://www.examtopics.com/discussions/splunk/view/23050-exam-splk-1001-topic-1-question-176-discussion/","unix_timestamp":1592037600,"isMC":true,"answers_community":["A (100%)"],"exam_id":198,"discussion":[{"comment_id":"123867","content":"A is correct","poster":"sunbird","upvote_count":"12","timestamp":"1609474800.0"},{"upvote_count":"8","comment_id":"109295","content":"A is correct","poster":"nonee125","timestamp":"1607856000.0"},{"poster":"Lonny","timestamp":"1718973600.0","content":"A is correct","upvote_count":"1","comment_id":"1102617"},{"content":"A is right answer","timestamp":"1701272100.0","poster":"Rider2053","comment_id":"909445","upvote_count":"1"},{"timestamp":"1696072200.0","poster":"kirtak","content":"Selected Answer: A\nyou cannot have two transforming commands next to each other","comment_id":"855655","upvote_count":"2"},{"content":"both stats and table are \"command\" so A is correct","comment_id":"841466","poster":"Alexi2415","upvote_count":"2","timestamp":"1694904840.0"},{"comment_id":"648827","timestamp":"1676803800.0","poster":"SlyLamp","upvote_count":"6","content":"Selected Answer: A\nI bet the admin failed this exam. Answer is A"},{"content":"Selected Answer: A\nA is confirmed","comment_id":"645255","timestamp":"1676097600.0","poster":"AlfredLow95","upvote_count":"3"},{"upvote_count":"2","content":"Selected Answer: A\nA is correct","timestamp":"1674099780.0","comment_id":"633296","poster":"falssa"},{"poster":"sborisv","upvote_count":"5","timestamp":"1673629200.0","content":"A. is correct\nFor that construction of { | stats table aa,bb,cc } Splunk says \"Error in 'stats' command: The argument 'table' is invalid.\"","comment_id":"630951"},{"timestamp":"1668020040.0","content":"Selected Answer: A\nA is correct","comment_id":"599178","poster":"Requete","upvote_count":"3"},{"poster":"Nandini_sr","timestamp":"1639556400.0","upvote_count":"1","comment_id":"382378","content":"A is correct"},{"comment_id":"227288","upvote_count":"1","poster":"labarcaremo635","timestamp":"1621922820.0","content":"A is correct, page 103 in PDF"},{"comment_id":"212771","timestamp":"1620129600.0","content":"page 103 in PDF for source. A is correct","upvote_count":"2","poster":"iguessillsignup"},{"content":"A is correct, stats already have an table output","upvote_count":"3","poster":"Glat","timestamp":"1616060520.0","comment_id":"181471"},{"upvote_count":"4","timestamp":"1611423600.0","comment_id":"142134","content":"A is correct answer","poster":"stallone"}],"question_id":86,"answer_images":[]},{"id":"gkZYAGNNfgm4LRXzHljJ","question_id":87,"answers_community":["A (100%)"],"choices":{"B":"Rare values by time","C":"Events with top value fields","A":"Top values by time","D":"Events with rare value fields"},"topic":"1","answer_images":[],"answer_description":"","exam_id":198,"answer":"A","question_images":[],"discussion":[{"comments":[{"content":"Did you rewrite the exam again using the discussions answers","poster":"Suz_bube7","upvote_count":"1","comment_id":"1184906","timestamp":"1727536320.0"}],"content":"I failed this exam using the answered the admin used. Thank Goodness for the discussion board","timestamp":"1723219020.0","poster":"tayodele1234","upvote_count":"1","comment_id":"1145678"},{"upvote_count":"1","poster":"Alexi2415","content":"it's \nTop values\nTop values by time\nRare values\nEvents with this field for field that has \"a\" in the front \nand the fields that have \"#\" in the front will be\nTop values\nTop values by time\nRare values\nEvents with this field \nAverage over time \nMaximum value over time \nMinimum value over time","timestamp":"1694905200.0","comment_id":"841470"},{"upvote_count":"1","timestamp":"1684534200.0","content":"Selected Answer: A\nA is correct","comment_id":"722301","poster":"kiki533"},{"upvote_count":"1","poster":"nqthien041292","content":"Selected Answer: A\nVote A","comment_id":"645916","timestamp":"1676216580.0"},{"upvote_count":"1","content":"Selected Answer: A\nA is correct","comment_id":"599182","timestamp":"1668020100.0","poster":"Requete"},{"poster":"GDanger","content":"PDF PAG.83 . Is A","comment_id":"305372","timestamp":"1631044260.0","upvote_count":"3"},{"comment_id":"227274","poster":"labarcaremo635","content":"A is correct, page 83 from PDF","timestamp":"1621921920.0","upvote_count":"1"},{"upvote_count":"1","timestamp":"1620130320.0","poster":"iguessillsignup","content":"page 114 of PDF, looks like it's saying that the only one on this list it DOESN'T have is D.","comment_id":"212778"},{"timestamp":"1611423660.0","poster":"stallone","content":"A is correct answer.","upvote_count":"2","comment_id":"142137"},{"poster":"parelo","content":"A is correct - Top values by time","comment_id":"123073","timestamp":"1609284960.0","upvote_count":"2"}],"question_text":"Which of the following reports is available in the Fields window?","isMC":true,"url":"https://www.examtopics.com/discussions/splunk/view/24400-exam-splk-1001-topic-1-question-177-discussion/","unix_timestamp":1593466560,"timestamp":"2020-06-29 23:36:00","answer_ET":"A"},{"id":"n2217KtXZEMUpr3qWhkJ","url":"https://www.examtopics.com/discussions/splunk/view/89117-exam-splk-1001-topic-1-question-178-discussion/","unix_timestamp":1669649040,"discussion":[{"upvote_count":"1","poster":"DarioReymag","content":"btool get this information","timestamp":"1732842420.0","comment_id":"729800"},{"timestamp":"1732811460.0","upvote_count":"1","content":"top command requires limit","comment_id":"729406","poster":"Uvasta"}],"question_images":[],"choices":{"D":"Visualization","A":"Events","C":"Statistics","B":"Patterns"},"exam_id":198,"question_id":88,"topic":"1","answers_community":[],"answer":"D","answer_images":[],"question_text":"In the Search and Reporting app, which tab displays timecharts and bar charts?","isMC":true,"answer_ET":"D","timestamp":"2022-11-28 16:24:00","answer_description":"Reference:\nhttps://docs.splunk.com/Documentation/Splunk/8.0.2/Search/Aboutreportingcommands"},{"id":"NQ7kvi7I8FCSXyYvDOqh","answer_description":"Reference:\nhttps://docs.splunk.com/Documentation/Splunk/8.0.3/SearchTutorial/Usefieldstosearch","unix_timestamp":1669649040,"answers_community":[],"answer":"D","choices":{"A":"index","B":"action","D":"sourcetype","C":"clientip"},"isMC":true,"exam_id":198,"question_text":"What will always appear in the Selected Fields list?","url":"https://www.examtopics.com/discussions/splunk/view/89118-exam-splk-1001-topic-1-question-179-discussion/","question_id":89,"timestamp":"2022-11-28 16:24:00","discussion":[{"poster":"DarioReymag","comment_id":"729802","content":"top command requires limit","upvote_count":"1","timestamp":"1732842420.0"},{"content":"Is it not C","upvote_count":"1","poster":"Uvasta","comment_id":"729407","timestamp":"1732811460.0"}],"topic":"1","question_images":[],"answer_ET":"D","answer_images":[]},{"id":"zdnjQAakHRFkv0B6sOQo","choices":{"D":"Alphabetically according to field name.","C":"In reverse chronological order.","B":"Randomly by default.","A":"In chronological order."},"timestamp":"2021-03-05 14:58:00","discussion":[{"poster":"Janna05","comment_id":"304193","timestamp":"1693915080.0","upvote_count":"6","content":"C is correct \npag 58 Displayed in reverse chronological order (newest first)"},{"upvote_count":"3","content":"Selected Answer: C\nC for sure","comment_id":"602562","poster":"emlch","timestamp":"1731764940.0"},{"comment_id":"597727","timestamp":"1730903040.0","content":"Selected Answer: C\nC is correct","poster":"Safra","upvote_count":"2"},{"comment_id":"527969","upvote_count":"2","poster":"HUGOTE","content":"C is OK","timestamp":"1721420100.0"}],"answer_images":[],"question_id":90,"isMC":true,"answers_community":["C (100%)"],"question_text":"How are events displayed after a search is executed?","answer":"C","exam_id":198,"unix_timestamp":1614952680,"topic":"1","question_images":[],"answer_ET":"C","answer_description":"","url":"https://www.examtopics.com/discussions/splunk/view/45959-exam-splk-1001-topic-1-question-18-discussion/"}],"exam":{"name":"SPLK-1001","lastUpdated":"12 Apr 2025","isBeta":false,"isImplemented":true,"id":198,"numberOfQuestions":207,"isMCOnly":false,"provider":"Splunk"},"currentPage":18},"__N_SSP":true}