{"pageProps":{"questions":[{"id":"LESKPTCQxMoqoLuvUcPK","question_images":[],"topic":"1","question_id":1,"answer_ET":"BC","url":"https://www.examtopics.com/discussions/vmware/view/74261-exam-5v0-2221-topic-1-question-1-discussion/","answer_images":[],"answers_community":["BC (100%)"],"isMC":true,"answer_description":"","exam_id":263,"timestamp":"2022-04-23 20:29:00","answer":"BC","unix_timestamp":1650738540,"discussion":[{"comment_id":"610827","poster":"StorageGuy","upvote_count":"8","content":"Selected Answer: BC\nShould be (B) and (C)","timestamp":"1654214640.0"},{"timestamp":"1662308340.0","upvote_count":"6","poster":"Mhelmy2025","comments":[{"upvote_count":"6","comment_id":"683183","poster":"exyuze","timestamp":"1664505600.0","content":"yes. almost all questions here not valid anymore. need to gather new question."}],"content":"Exam questions changed","comment_id":"659385"},{"comment_id":"950952","content":"I took the test today, the dump is no longer valid. No similar question.","timestamp":"1689276960.0","upvote_count":"1","poster":"vvrrdf2810"},{"poster":"9f2738e","upvote_count":"3","comment_id":"865944","content":"Hello freinds , the question are still valid or not please confirm i plan to pass the exam next wednesday","timestamp":"1681093680.0"},{"timestamp":"1680946920.0","upvote_count":"5","comment_id":"864587","poster":"simocelio","content":"i confirm this dump is not valid exam taken 07.04.2023"},{"comments":[{"comment_id":"854387","comments":[{"upvote_count":"2","comments":[{"comments":[{"comment_id":"903920","timestamp":"1684750740.0","poster":"ultrahorst","upvote_count":"1","content":"same for me. took 5V0-22.21 and not a single question of it was from this dump."}],"poster":"virtualPenguin","content":"Qs are not same. I took and failed.","timestamp":"1683533580.0","upvote_count":"2","comment_id":"891911"}],"poster":"simocelio","timestamp":"1680168780.0","comment_id":"855557","content":"@JLF_VMW can you answer virtualpenguin please"}],"content":"@JLF_VMW which exam did you take? \n5V0-22.21 or 5V0-22.23?","timestamp":"1680092880.0","poster":"virtualPenguin","upvote_count":"2"},{"poster":"9f2738e","upvote_count":"2","timestamp":"1682090340.0","content":"are you sure that you passed 5V0-22.21 not 23 because all dump that i found have the same questions","comment_id":"876668"}],"comment_id":"849271","timestamp":"1679659560.0","upvote_count":"3","poster":"JLF_VMW","content":"Now it's a different exam!"},{"upvote_count":"2","content":"Took exam on Feb 3 2023. Questions still valid.","comments":[{"timestamp":"1677841980.0","content":"Sorry March 3 2023 and the dumps are still valid","upvote_count":"2","poster":"mkvicky21","comment_id":"827904"}],"timestamp":"1677841920.0","comment_id":"827903","poster":"mkvicky21"},{"comment_id":"774132","upvote_count":"2","content":"Hi guys, are the questions valid? I plan my exam in the mid of February. Thanks!","poster":"suuruu","timestamp":"1673585820.0"},{"poster":"rudyy","content":"yes. agree with @Mhelmy2025, almost all questions here not valid anymore. need to gather new question.","upvote_count":"3","comment_id":"749675","timestamp":"1671442500.0"},{"comment_id":"748977","timestamp":"1671372060.0","upvote_count":"1","poster":"spamfach","content":"Selected Answer: BC\nCorrect answer B & C"},{"comment_id":"719270","timestamp":"1668563460.0","poster":"geoo21","content":"Hi guys, please be honest, is the question in this exam still valid? its about my life & dead :((","upvote_count":"2","comments":[{"upvote_count":"6","timestamp":"1668685140.0","content":"not valid","comment_id":"720418","poster":"AZIZZI"}]},{"timestamp":"1667679240.0","comment_id":"711991","content":"Are the questions valid, please?","poster":"AAHR96","comments":[{"comment_id":"713456","upvote_count":"7","poster":"bobbyjudith","timestamp":"1667877960.0","content":"not valid, exams changed"},{"timestamp":"1671658440.0","content":"I have the valid questions...","upvote_count":"1","comment_id":"752780","poster":"SerchRomo","comments":[{"content":"could you please share with us the valid question","poster":"9f2738e","timestamp":"1681154220.0","upvote_count":"1","comment_id":"866572"}]}],"upvote_count":"4"},{"timestamp":"1667057940.0","poster":"tayab","content":"Selected Answer: BC\nsince performance of storage needed its means more disk groups , more disk group means more cache and capacity drives.","comment_id":"707295","upvote_count":"1"},{"content":"Are the questions on this site still valid?","timestamp":"1666611480.0","comments":[{"content":"exams changed, not valid","poster":"bobbyjudith","comments":[{"comments":[{"upvote_count":"4","poster":"bobbyjudith","timestamp":"1668121920.0","content":"i took the exam and not even 1 Question similar","comment_id":"715606"}],"upvote_count":"3","poster":"Montecchius","comment_id":"715011","content":"Some people say exam questions have changed other say the opposite so i'm not sure whether or not this questions are valid.","timestamp":"1668066300.0"}],"timestamp":"1667877900.0","upvote_count":"4","comment_id":"713455"},{"comments":[{"timestamp":"1667999400.0","comments":[{"upvote_count":"4","timestamp":"1668121980.0","poster":"bobbyjudith","content":"Not true, i took the exam and its not same","comment_id":"715608"}],"content":"are you sure? is it true?","comment_id":"714586","upvote_count":"1","poster":"venz2020"}],"timestamp":"1667752380.0","content":"Just took it last week and all the questions here are on the exam.","poster":"StephS","upvote_count":"2","comment_id":"712474"}],"upvote_count":"3","comment_id":"702966","poster":"venz2020"},{"upvote_count":"1","comment_id":"639893","timestamp":"1659240240.0","content":"should be B AND C","poster":"Pacino_Yang"},{"upvote_count":"1","content":"Selected Answer: BC\n1 cache disk and max 7 capacity disk per disk group. E is WRONG.","timestamp":"1657608780.0","poster":"antoninStrnadA","comment_id":"630340"},{"comment_id":"592444","content":"https://docs.vmware.com/en/VMware-vSphere/7.0/vsan-703-planning-deployment-guide.pdf","timestamp":"1650978420.0","upvote_count":"1","poster":"fr33exam"},{"upvote_count":"3","content":"Should be (B) and (C)","timestamp":"1650738540.0","comment_id":"590747","poster":"Tsam09"}],"choices":{"A":"Add additional hosts, with capacity devices only, and then stream the cache from the other hosts.","E":"Add to the existing disk groups two cache devices and the eight capacity devices.","B":"Add cache and capacity devices to the compute-only hosts.","C":"Add additional cache and capacity devices to the existing data nodes.","D":"Add additional compute-only hosts from the vSAN cluster."},"question_text":"A vSAN administrator, who has a cluster that has both compute-only and vSAN ReadyNodes, recently received a request to deploy a new application with higher storage performance requirements than what are currently available.\nWhat are two ways the administrator can reconfigure the vSAN cluster to obtain this additional performance? (Choose two.)"},{"id":"vuyS4npsWtqbeCAks14g","question_images":[],"unix_timestamp":1653603420,"question_id":2,"timestamp":"2022-05-27 00:17:00","answer_ET":"BE","url":"https://www.examtopics.com/discussions/vmware/view/76322-exam-5v0-2221-topic-1-question-10-discussion/","answers_community":["BE (100%)"],"question_text":"Which two conditions should be verified before removing an ESXi host from a vSAN cluster? (Choose two.)","discussion":[{"content":"Correct answer: B & E","comment_id":"753329","poster":"rhosp13","upvote_count":"1","timestamp":"1671716340.0"},{"upvote_count":"2","comment_id":"748975","timestamp":"1671371880.0","poster":"spamfach","content":"Selected Answer: BE\nCorrect answer B & E"},{"poster":"Abita","content":"Selected Answer: BE\nCorrect answer: B & E.\nYou need to put the host in Maintenance mode, otherwise vSAN will not allow that host to remove from the cluster.\nBefore you need to make sure that the data is migrated fully","timestamp":"1669269960.0","upvote_count":"1","comment_id":"725587"},{"comment_id":"646615","timestamp":"1660460520.0","content":"Selected Answer: BE\nCorrect answer: B & E.\nYou need to put the host in Maintenance mode, otherwise vSAN will not allow that host to remove from the cluster.\nBefore you need to makesure that the data migrated fully \n\nSo the answer is B and E","upvote_count":"1","poster":"ekarjun"},{"upvote_count":"1","content":"Correct answer: B & E","timestamp":"1654872900.0","poster":"ariel009","comment_id":"614598"},{"upvote_count":"1","poster":"StorageGuy","timestamp":"1654215840.0","content":"Selected Answer: BE\nhttps://kb.vmware.com/s/article/2148975","comment_id":"610840"},{"poster":"R33w_10","content":"Selected Answer: BE\nB and E according to the provided reference\nhttps://kb.vmware.com/s/article/2148975","timestamp":"1653603420.0","comment_id":"607813","upvote_count":"1"}],"isMC":true,"topic":"1","exam_id":263,"choices":{"D":"Encryption is disabled","E":"ESXi host is in maintenance mode","C":"Performance Service is disabled","A":"Resyncs are running","B":"Data evacuation is complete"},"answer_description":"","answer_images":[],"answer":"BE"},{"id":"cJPNS0ff4gzILVMnh8ll","answers_community":["D (100%)"],"choices":{"B":"100GB","A":"150 GB","D":"200GB","C":"133GB"},"topic":"1","answer_ET":"D","question_images":["https://www.examtopics.com/assets/media/exam-media/04291/0000900001.jpg"],"isMC":true,"question_id":3,"discussion":[{"content":"I think that it is D correct, because with raid 1 the data is mirrored, so 200GB consumed.","comment_id":"606751","poster":"sebasslp98","timestamp":"1653400560.0","comments":[{"timestamp":"1656078480.0","comments":[{"upvote_count":"1","content":"But the node has recovered and the \"total VMDK storage consumed\" is 200GB.. I think D","timestamp":"1658731980.0","comment_id":"636501","poster":"Padulka"}],"upvote_count":"1","comment_id":"621685","content":"Raid is performed on the node level..so it should be 100Gb","poster":"fr33exam"}],"upvote_count":"5"},{"timestamp":"1669270740.0","poster":"Abita","content":"Selected Answer: D\nB/c we have used Raid 1 which will create one more additional copy to satisfy the FTT level. so the total size is 200GB.","upvote_count":"2","comment_id":"725592"},{"upvote_count":"2","timestamp":"1666727580.0","content":"Are this questions still valid?","comment_id":"704142","poster":"edk3r13"},{"upvote_count":"3","content":"Selected Answer: D\nD is correct","poster":"rhosp13","comment_id":"700836","timestamp":"1666354020.0"},{"timestamp":"1666053540.0","content":"Selected Answer: D\nHas to be D","comment_id":"697767","upvote_count":"3","poster":"rkurupt"},{"poster":"pongy","content":"RAID is performed at the object level (VMDK) not the node level. We don't know how much data the VM has consumed within the VMDK object (as space is thin provisioned(default), the 100GB is not guaranteed to be consumed). Based on the numbers provided though, RAID 1 mirroring will create two objects on two hosts (plus a witness object on the witness host). Total space used is 200GB (plus a few mb on the witness). D.","upvote_count":"1","timestamp":"1662196560.0","comment_id":"658274"}],"url":"https://www.examtopics.com/discussions/vmware/view/74774-exam-5v0-2221-topic-1-question-11-discussion/","answer":"D","answer_images":[],"timestamp":"2022-04-28 15:09:00","exam_id":263,"answer_description":"","question_text":"In a 2-node vSAN cluster, one node has recovered from failure with FTT=1 and RAID-1 storage policy.\nRefer to the exhibit:\n//IMG//\n\nWhat is the total VMDK storage consumed?","unix_timestamp":1651151340},{"id":"IHwhynw0VIyJvPGDFetx","question_text":"A vSAN administrator is implementing deduplication and compression on a vSAN all-flash cluster but wants the VMs to remain operational. The details are as follows:\n✑ There are 4 nodes in the vSAN cluster.\n✑ Existing VMs use a RAID-5 storage policy.\nWhich action should the vSAN administrator take to meet this goal?","question_id":4,"choices":{"A":"Use explicit fault domains.","D":"Use the Allow Reduced Redundancy option.","C":"Change the existing VM storage policy to RAID-6.","B":"Enable TRIM/UNMAP."},"answers_community":["D (100%)"],"discussion":[{"poster":"Abita","timestamp":"1669271280.0","comment_id":"725594","content":"Selected Answer: D\nAllow Reduced Redundancy option.","upvote_count":"1"},{"poster":"cheo","comment_id":"622272","timestamp":"1656194520.0","content":"Selected Answer: D\nhttps://docs.vmware.com/es/VMware-vSphere/7.0/com.vmware.vsphere.vsan.doc/GUID-125B2B04-FBB9-43AB-8AF9-E7179734BC7C.html#GUID-125B2B04-FBB9-43AB-8AF9-E7179734BC7C","upvote_count":"1"},{"content":"Selected Answer: D\nUse the Allow Reduced Redundancy option.","upvote_count":"1","comment_id":"610841","poster":"StorageGuy","timestamp":"1654216020.0"}],"isMC":true,"unix_timestamp":1654216020,"url":"https://www.examtopics.com/discussions/vmware/view/76530-exam-5v0-2221-topic-1-question-12-discussion/","exam_id":263,"topic":"1","answer":"D","timestamp":"2022-06-03 02:27:00","question_images":[],"answer_ET":"D","answer_images":[],"answer_description":""},{"id":"ogf17pfrUZ0HLhxKqBUT","exam_id":263,"isMC":true,"discussion":[{"upvote_count":"1","content":"D. Launch Quickstart to Add Hosts to a vSAN Cluster\nthe question is add host not configure host. \nUse a host profile to configure all host added is the next step.","timestamp":"1697003340.0","comment_id":"1040225","poster":"seijilo"},{"timestamp":"1684448460.0","upvote_count":"1","comment_id":"901529","poster":"jesusmac","content":"Selected Answer: D\nthey both worrk but host profiles is more work. it doesnt help that it doesnt say if the cluster was created with quickstart"},{"content":"Selected Answer: D\nI think Quick start is correct.","timestamp":"1677187260.0","upvote_count":"3","comment_id":"819764","poster":"uchiken"},{"timestamp":"1675194240.0","upvote_count":"1","content":"Selected Answer: D\nhttps://docs.vmware.com/en/VMware-vSphere/7.0/com.vmware.vsphere.vsan-planning.doc/GUID-7BC09239-46BD-46FD-B803-95244CCBC8F4.html","poster":"benycom","comment_id":"794562"},{"timestamp":"1670970660.0","content":"A\nConfiguring Hosts Using Host Profile\nWhen you have multiple hosts in the vSAN cluster, you can use the profile of an existing vSAN\nhost to configure the rest of the hosts in the vSAN cluster.\nThe host profile includes information about storage configuration, network configuration, and\nother characteristics of the host. If you are planning to create a cluster with many hosts, such as\n8, 16, 32, or 64 hosts, use the host profile feature. Host profiles enable you to add more than one\nhost at a time to the vSAN cluster.\nPrerequisites\nn Verify that the host is in maintenance mode.\nn Verify that the hardware components, drivers, firmware, and storage I/O controllers are listed\nin the VMware Compatibility Guide at http://www.vmware.com/resources/compatibility/\nsearch.php.","upvote_count":"2","comment_id":"744502","poster":"Coolio"},{"content":"Selected Answer: A\nWhen you have multiple hosts in the vSAN cluster, you can use the profile of an existing vSAN host to configure the rest of the hosts in the vSAN cluster.\nThe host profile includes information about storage configuration, network configuration, and other characteristics of the host. If you are planning to create a cluster with many hosts, such as 8, 16, 32, or 64 hosts, use the host profile feature. Host profiles enable you to add more than one host at a time to the vSAN cluster.","timestamp":"1670857320.0","poster":"DonatasQ","comment_id":"742953","upvote_count":"1"},{"comment_id":"725612","poster":"Abita","timestamp":"1669273080.0","upvote_count":"1","content":"Selected Answer: A\nThe Quickstart workflow is designed for new clusters. When you upgrade an existing vSAN cluster to 6.7 Update 1 or later, the Quickstart workflow appears. Skip the Quickstart workflow and continue to manage the cluster through vCenter Server.\n\n If you are planning to create a cluster with many hosts, such as 8, 16, 32, or 64 hosts, use the host profile feature. Host profiles enable you to add more than one host at a time to the vSAN cluster."},{"poster":"tquocanh","timestamp":"1663570080.0","comment_id":"673002","content":"Selected Answer: D\nI think, Answer: D\nBecause in the question I see \"to add to...\" rather than the hosts configuration already in existing vSAN cluster.","upvote_count":"2"},{"poster":"alexandreoz","comment_id":"649530","timestamp":"1661023380.0","upvote_count":"1","content":"Selected Answer: A\nFor multiple hosts, you can use Host Profile. Answer is A."},{"upvote_count":"1","content":"Selected Answer: A\nHost profile is the best way in this option for quick configuration\n\nAnswer is A","poster":"ekarjun","comment_id":"646708","timestamp":"1660475280.0"},{"poster":"Tunananana","timestamp":"1659512880.0","content":"Selected Answer: A\nWhen you have multiple hosts in the vSAN cluster, you can use the profile of an existing vSAN\nhost to configure the rest of the hosts in the vSAN cluster.","comment_id":"641695","upvote_count":"1"},{"poster":"Pacino_Yang","comment_id":"639900","timestamp":"1659241260.0","content":"Selected Answer: A\nShould be A","upvote_count":"1"},{"content":"Selected Answer: A\nThe host profile includes information about storage configuration, network configuration, and\nother characteristics of the host. If you are planning to create a cluster with many hosts, such as\n8, 16, 32, or 64 hosts, use the host profile feature. Host profiles enable you to add more than one\nhost at a time to the vSAN cluster.","upvote_count":"1","timestamp":"1658885820.0","poster":"udarad","comment_id":"637732"},{"content":"Selected Answer: A\nPage 31 of the guide says,\n\nWhen you have multiple hosts in the vSAN cluster, you can use the profile of an existing vSAN\nhost to configure the rest of the hosts in the vSAN cluster.\nThe host profile includes information about storage configuration, network configuration, and\nother characteristics of the host. If you are planning to create a cluster with many hosts, such as\n8, 16, 32, or 64 hosts, use the host profile feature. Host profiles enable you to add more than one\nhost at a time to the vSAN cluster.","upvote_count":"1","poster":"addigate","timestamp":"1655709720.0","comment_id":"619071"},{"upvote_count":"1","timestamp":"1653476760.0","poster":"jb844","comments":[{"upvote_count":"1","poster":"poochiedaddy","comments":[{"timestamp":"1665124500.0","poster":"carlosmasetools","upvote_count":"2","comment_id":"688389","content":"the correct is D.\nwe need add to a created cluster, no create a new cluster\nIn the same document\nPage 29, quickstart \"you can use the Quickstart workflow to\nadd hosts and storage devices to the cluster\"\npage 31, host profile \" If you are planning to create a cluster.......use host profile\""}],"comment_id":"625400","timestamp":"1656615240.0","content":"Answer: A\nPage 31 of the very same Guide"}],"comment_id":"607180","content":"Selected Answer: D\npage 29 of admin guide\nhttps://docs.vmware.com/en/VMware-vSphere/7.0/vsan-703-administration-guide.pdf"}],"question_id":5,"answer_images":[],"choices":{"A":"Use a Host Profile that was extracted from an existing host.","D":"Launch Quickstart to Add Hosts to a vSAN Cluster","C":"Run vim-cmd to capture, and apply the configuration from an existing host.","B":"Clone the ESXi boot partition to all new hosts, since the hardware is identical."},"answer_description":"","timestamp":"2022-05-25 13:06:00","answer":"D","topic":"1","question_text":"A vSAN administrator was presented with 30 additional vSAN ReadyNodes to add to an existing vSAN cluster. There is only one administrator to complete this task.\nWhat is the fastest approach?","answers_community":["D (50%)","A (50%)"],"question_images":[],"url":"https://www.examtopics.com/discussions/vmware/view/76276-exam-5v0-2221-topic-1-question-13-discussion/","answer_ET":"D","unix_timestamp":1653476760}],"exam":{"name":"5V0-22.21","numberOfQuestions":76,"isBeta":false,"lastUpdated":"12 Apr 2025","provider":"Vmware","isImplemented":true,"id":263,"isMCOnly":true},"currentPage":1},"__N_SSP":true}