{"pageProps":{"questions":[{"id":"SFPPmGLRg0xci89ZQV2K","exam_id":73,"url":"https://www.examtopics.com/discussions/microsoft/view/74338-exam-dp-900-topic-1-question-44-discussion/","question_id":231,"isMC":true,"answer":"A","choices":{"B":"Infrastructure as a service (IaaS)","A":"Platform as a service (PaaS)","D":"on-premises","C":"Microsoft SQL Server"},"answer_ET":"A","answer_images":[],"question_images":[],"question_text":"Which type of database is Azure Database for PostgreSQL?","unix_timestamp":1650813900,"topic":"1","answers_community":["A (95%)","5%"],"answer_description":"","timestamp":"2022-04-24 17:25:00","discussion":[{"comment_id":"592347","upvote_count":"33","poster":"bfan95","timestamp":"1650972240.0","content":"Correct answer: A, PAAS"},{"timestamp":"1650813900.0","content":"The answer is correct - A","poster":"Afetik","comment_id":"591137","upvote_count":"14"},{"content":"Selected Answer: A\nAzure Database for PostgreSQL is a fully managed database service provided by Azure. It handles database maintenance tasks such as patching, backups, scaling, and high availability, making it a PaaS offering.","comment_id":"1341447","poster":"man5484","upvote_count":"1","timestamp":"1737006720.0"},{"poster":"Bin_Hashim","comment_id":"1314022","upvote_count":"1","timestamp":"1731938580.0","content":"Answer: A. Platform as a service (PaaS)\n\nAzure Database for PostgreSQL is a fully managed database service, which is categorized as Platform as a Service (PaaS)."},{"content":"Selected Answer: A\nPaaS is the answer","upvote_count":"1","poster":"TKC_2023","comment_id":"1263358","timestamp":"1723274340.0"},{"poster":"_Vijay_","upvote_count":"1","timestamp":"1721665380.0","content":"Selected Answer: A\nYep! It is correct.","comment_id":"1253182"},{"poster":"okayhey","upvote_count":"1","comment_id":"1168350","timestamp":"1709844540.0","content":"All database services are PaaS"},{"content":"Option A","poster":"AGTraining","comment_id":"1162461","upvote_count":"1","timestamp":"1709204220.0"},{"comment_id":"1134881","upvote_count":"1","timestamp":"1706527800.0","content":"The answer is A, PaaS. Azure Databases uses DBaaS, which falls under PaaS.","poster":"BXtheCoder"},{"timestamp":"1704872880.0","comment_id":"1118280","content":"Passed exam on 9/1/2024, got 984/1000.\nMy answer was PAAS","upvote_count":"4","poster":"[Removed]"},{"timestamp":"1701198660.0","content":"Azure Database for PostgreSQL is falls under the category of Database as a Service (DBaaS) or Platform as a Service (PaaS).","comment_id":"1082868","poster":"ravinperera","upvote_count":"2"},{"timestamp":"1693593720.0","content":"Selected Answer: A\nAll DB offerings in Azure are PaaS, except when installed in a VM (then it is IaaS).","comment_id":"996352","upvote_count":"9","poster":"AZFabio"},{"poster":"MannyJZ","comment_id":"975991","upvote_count":"2","timestamp":"1691524500.0","content":"On exam today 08/08/23"},{"upvote_count":"1","poster":"rohirag","comment_id":"950474","content":"Selected Answer: A\nPaaS. \nhttps://learn.microsoft.com/en-us/training/modules/explore-provision-deploy-relational-database-offerings-azure/3-azure-database-open-source","timestamp":"1689236460.0"},{"timestamp":"1684244940.0","poster":"chematab","comment_id":"899252","upvote_count":"1","content":"Selected Answer: A\nCorrect Answer"},{"content":"Selected Answer: A\nCorrect Answer","timestamp":"1677898920.0","upvote_count":"2","comment_id":"828565","poster":"chiiiweiii"},{"poster":"tangerine141","comment_id":"817557","content":"Selected Answer: A\nCorrect answer: A, PAAS","timestamp":"1677049620.0","upvote_count":"1"},{"content":"Selected Answer: A\nPaaS is the correct answer.","timestamp":"1676735100.0","comment_id":"813228","upvote_count":"1","poster":"Joanna0"},{"content":"Selected Answer: A\nPlatform as a service","poster":"ravick4u","timestamp":"1675872000.0","comment_id":"802208","upvote_count":"1"},{"comment_id":"800536","poster":"smgk","content":"Selected Answer: A\nanswer: paas","timestamp":"1675743840.0","upvote_count":"1"},{"content":"Selected Answer: A\nCorrect answer: A, PAAS","poster":"Annelijn","upvote_count":"2","timestamp":"1668500160.0","comment_id":"718586"},{"content":"Selected Answer: A\nCorrect answer: A, PAAS","poster":"MrTurbo","comment_id":"707968","timestamp":"1667155140.0","upvote_count":"3"},{"content":"was on exam today 09/30/22","upvote_count":"4","timestamp":"1664545260.0","poster":"blackskies","comment_id":"683600"},{"timestamp":"1659946980.0","poster":"T4321","upvote_count":"5","content":"Selected Answer: A\nAnswer is 'A'","comment_id":"644021"},{"content":"https://docs.microsoft.com/en-us/azure/postgresql/single-server/overview-postgres-choose-server-options","poster":"Edriv","timestamp":"1657374360.0","comment_id":"629194","upvote_count":"3"},{"comment_id":"626068","timestamp":"1656753480.0","upvote_count":"2","poster":"Eltooth","content":"Selected Answer: A\nA is correct answer : PaaS"},{"timestamp":"1656594120.0","poster":"simplementeluca","comment_id":"625266","upvote_count":"1","content":"A- PaaS I'm sure."},{"content":"Selected Answer: B\nThe answer is correct","poster":"Gautam123","comments":[{"timestamp":"1654359120.0","poster":"Gautam123","upvote_count":"5","content":"Sorry A","comment_id":"611493"}],"upvote_count":"2","timestamp":"1654359120.0","comment_id":"611492"},{"content":"yes that's corret","poster":"geeeogeee","timestamp":"1653138120.0","comment_id":"604897","upvote_count":"2"},{"comment_id":"601884","upvote_count":"7","content":"Selected Answer: A\nPAAS is the ans","timestamp":"1652585640.0","poster":"EXODUS33"}]},{"id":"sZSibvFtXXjSROtnyyYs","question_id":232,"answers_community":["A (100%)"],"timestamp":"2022-04-23 10:52:00","unix_timestamp":1650703920,"choices":{"D":"Azure Cosmos DB","B":"Azure Queue storage","C":"Azure Blob storage","A":"Azure Data Lake Storage"},"answer_description":"","isMC":true,"answer":"A","exam_id":73,"question_images":[],"question_text":"Which storage solution supports access control lists (ACLs) at the file and folder level?","topic":"1","answer_ET":"A","answer_images":[],"url":"https://www.examtopics.com/discussions/microsoft/view/74207-exam-dp-900-topic-1-question-45-discussion/","discussion":[{"content":"Correct Answer is A. Azure Data Lake Storage","comment_id":"590493","upvote_count":"25","timestamp":"1650703920.0","poster":"svetlanam"},{"upvote_count":"1","content":"Selected Answer: A\nAzure Data Lake Storage","comment_id":"1356024","poster":"Swamy90572","timestamp":"1739436240.0"},{"timestamp":"1737006900.0","content":"Selected Answer: A\nAzure Data Lake Storage supports access control lists (ACLs) at the file and folder level, allowing fine-grained control over access permissions. This is particularly useful for big data analytics workloads.","comment_id":"1341451","poster":"man5484","upvote_count":"1"},{"upvote_count":"1","timestamp":"1723274340.0","poster":"TKC_2023","comment_id":"1263359","content":"Selected Answer: A\nCorrect Answer is A. Azure Data Lake Storage"},{"timestamp":"1709211180.0","comment_id":"1162545","content":"Option A","poster":"AGTraining","upvote_count":"1"},{"poster":"AZFabio","comment_id":"996355","upvote_count":"2","timestamp":"1693593900.0","content":"Selected Answer: A\ncorrect"},{"poster":"srgopalkr","comment_id":"964366","upvote_count":"3","timestamp":"1690435200.0","content":"This is a trick question as both Azure Blob Storage & Azure Data Lake support ACL's at the file and directory level leveraging Security principal (user, group, service principal, or managed identity). Additionally, Azure Data Lake storage system is based on Azure Blob Storage system. \nHowever Azure Data Lake Gen2, implements ACL differently in comparison to Azure Blob Storage, with the former supporting Azure RBAC & POSIX ACL's. Azure Blob Storage implements access control using SAS and AAD authentication.\nSo in my opinion, both A & C are correct."},{"comment_id":"939830","upvote_count":"1","poster":"HRKK","content":"CORRECT ANSWER A","timestamp":"1688207040.0"},{"upvote_count":"3","content":"in the exam 26/03","timestamp":"1679836440.0","poster":"ahmedkmj","comment_id":"851046"},{"comment_id":"828566","upvote_count":"2","content":"Correct Answer","timestamp":"1677898920.0","poster":"chiiiweiii"},{"content":"Selected Answer: A\nhttps://learn.microsoft.com/en-us/azure/storage/blobs/data-lake-storage-access-control#about-acls","timestamp":"1676735160.0","poster":"Joanna0","comment_id":"813230","upvote_count":"1"},{"content":"Selected Answer: A\nA. Azure Data Lake Storage","timestamp":"1675872060.0","poster":"ravick4u","upvote_count":"1","comment_id":"802209"},{"poster":"nilsoncarlosf","comment_id":"733271","content":"Correct is A","upvote_count":"1","timestamp":"1669942200.0"},{"poster":"JA2018","content":"Selected Answer: A\nAgreed, A is the correct option. duplicated question","timestamp":"1667395620.0","comment_id":"709829","upvote_count":"2"},{"upvote_count":"3","comment_id":"691552","content":"on exam 10 Oct 2022","timestamp":"1665443280.0","poster":"Albertopology"},{"timestamp":"1660236660.0","poster":"ria97","comment_id":"645550","upvote_count":"3","content":"Was in exam 11/08. Correct answer"},{"content":"Exam: 19.07.22","timestamp":"1658234820.0","poster":"Breeze21","upvote_count":"3","comment_id":"633561"},{"upvote_count":"2","poster":"Eltooth","comment_id":"626069","content":"Selected Answer: A\nA is correct answer. ADL","timestamp":"1656753540.0"},{"content":"Selected Answer: A\nA the correct","timestamp":"1656594780.0","poster":"simplementeluca","comment_id":"625273","upvote_count":"1"},{"upvote_count":"3","comment_id":"601885","content":"Selected Answer: A\nData lake is the ans","poster":"EXODUS33","timestamp":"1652585700.0"},{"content":"Selected Answer: A\nThe answer is A","comment_id":"597602","timestamp":"1651820640.0","poster":"Duncan567710","upvote_count":"2"},{"poster":"bfan95","upvote_count":"2","comment_id":"592349","content":"Selected Answer: A\nAnswer: A","timestamp":"1650972300.0"}]},{"id":"hxOTd7hJeRUSe0Gw4mO6","answer_images":["https://www.examtopics.com/assets/media/exam-media/04277/0006300001.png"],"question_images":["https://www.examtopics.com/assets/media/exam-media/04277/0006200001.png"],"discussion":[{"timestamp":"1666690260.0","comment_id":"591505","content":"treemap","poster":"bfan95","upvote_count":"30"},{"content":"I took the exam 12.04.2023 and got 1000, 100% score; this question appeared, correct answer:\ntreemap","timestamp":"1697107080.0","upvote_count":"7","poster":"mamahani","comment_id":"868188"},{"content":"A treemap is a chart of colored rectangles where the size of each rectangle represents the relative value of each item. It can also display hierarchical data, with rectangles nested within larger ones to represent different levels of the hierarchy.","upvote_count":"1","comment_id":"1341456","timestamp":"1737007200.0","poster":"man5484"},{"comment_id":"1186033","poster":"heobanten04","timestamp":"1727685000.0","content":"I took the exam 30.03.2024 and got 936; this question appeared, correct answer:\ntreemap","upvote_count":"2"},{"content":"treemap","comment_id":"1162548","poster":"AGTraining","timestamp":"1724929020.0","upvote_count":"1"},{"upvote_count":"1","content":"Yeah. The answer is Treemap.","comment_id":"1134883","timestamp":"1722245520.0","poster":"BXtheCoder"},{"upvote_count":"1","poster":"james2033","comment_id":"1054602","content":"treemap - colored rectangles, can be hierarchical.","timestamp":"1714137300.0"},{"poster":"HRKK","timestamp":"1704111900.0","content":"CORRECT","upvote_count":"1","comment_id":"939832"},{"content":"Correct Answer","upvote_count":"2","timestamp":"1693789380.0","poster":"chiiiweiii","comment_id":"828567"},{"comments":[{"content":"No. C is a Scatter Plot which is used to analyze what happens to a variable when another variable changes, consist of many dots on the chart. Treemap consists of coloured rectangles.","timestamp":"1722245580.0","comment_id":"1134886","upvote_count":"1","poster":"BXtheCoder"},{"upvote_count":"1","timestamp":"1693159140.0","content":"Wrong, it is treemap","poster":"Alex4190","comment_id":"824105"}],"upvote_count":"1","comment_id":"809610","content":"answer should be C option","poster":"jharnakalan","timestamp":"1692099780.0"},{"timestamp":"1680183720.0","content":"was on exam today 09/30/22","upvote_count":"4","poster":"blackskies","comment_id":"683601"},{"poster":"gabrisiq","content":"Colored Rectangles = Treemap","comment_id":"642529","timestamp":"1675533480.0","upvote_count":"4"},{"poster":"Eltooth","comment_id":"626070","content":"Tree map is correct answer.","timestamp":"1672658340.0","upvote_count":"2"},{"upvote_count":"1","poster":"WWDITDA","content":"Treemap - Correct.","timestamp":"1671567120.0","comment_id":"619421"},{"poster":"Manoj6","content":"Treemap is the correct answer","comment_id":"606469","upvote_count":"2","timestamp":"1669271100.0"},{"poster":"dk87","content":"Exam: 05/18/2022","timestamp":"1668776880.0","upvote_count":"3","comment_id":"603245"}],"url":"https://www.examtopics.com/discussions/microsoft/view/74426-exam-dp-900-topic-1-question-46-discussion/","question_text":"HOTSPOT -\nSelect the answer that correctly completes the sentence.\nHot Area:\n//IMG//","topic":"1","question_id":233,"timestamp":"2022-04-25 11:31:00","unix_timestamp":1650879060,"answer_ET":"","answer_description":"A treemap chart divides the chart area into rectangles that represent the different levels and relative sizes of the data hierarchy.\nReference:\nhttps://docs.microsoft.com/en-us/sql/reporting-services/report-design/tree-map-and-sunburst-charts-in-reporting-services?view=sql-server-ver15","exam_id":73,"answers_community":[],"isMC":false,"answer":""},{"id":"RSjzYIaPL3ty8GeGM5qf","discussion":[{"content":"Answer should be C","comments":[{"upvote_count":"1","poster":"ha1p","content":"agree w/ you","timestamp":"1680128280.0","comment_id":"855021"}],"poster":"sallymaher","timestamp":"1650460260.0","comment_id":"588692","upvote_count":"144"},{"poster":"JoJoY","content":"Selected Answer: C\nThe answer is C","comments":[{"poster":"skaha","content":"which is not characteristic of Batch processing>>>Then the answer is D","timestamp":"1650534780.0","comment_id":"589239","upvote_count":"4"}],"comment_id":"589027","timestamp":"1650503400.0","upvote_count":"45"},{"content":"Selected Answer: C\nC. There is a noticeable time delay between ingesting data and obtaining the data processing results","upvote_count":"1","timestamp":"1739436720.0","poster":"Swamy90572","comment_id":"1356026"},{"upvote_count":"1","content":"Selected Answer: C\nBatch processing involves collecting data over a period of time and then processing it all at once, which introduces a noticeable delay between data ingestion and the processing results. This is in contrast to real-time processing, where data is processed immediately as it is received.","poster":"man5484","timestamp":"1737007380.0","comment_id":"1341458"},{"poster":"cdiggy22","comment_id":"1338168","upvote_count":"1","content":"Selected Answer: C\nThe correct answer is C","timestamp":"1736389620.0"},{"timestamp":"1726865340.0","upvote_count":"1","poster":"ash_7074","content":"Selected Answer: C\nC is th right one","comment_id":"1287054"},{"poster":"profesorklaus","timestamp":"1725697620.0","comment_id":"1279938","upvote_count":"2","content":"Selected Answer: C\nC is correct answer"},{"comment_id":"1253184","timestamp":"1721665620.0","upvote_count":"2","content":"Selected Answer: C\nThe \"D\" answer is a BIG time wrong answer.","poster":"_Vijay_"},{"poster":"Jikkuz","comment_id":"1214815","content":"Selected Answer: C\nC is the answer","timestamp":"1716279720.0","upvote_count":"1"},{"poster":"heobanten04","content":"I took the exam 30.03.2024 and got 936; this question appeared, correct answer: C","comment_id":"1186034","timestamp":"1711794660.0","upvote_count":"6"},{"poster":"IK13","comment_id":"1181287","upvote_count":"2","content":"C\nhttps://learn.microsoft.com/en-us/training/modules/explore-fundamentals-stream-processing/2-batch-stream","timestamp":"1711247580.0"},{"content":"option C","poster":"AGTraining","timestamp":"1709211480.0","comment_id":"1162549","upvote_count":"1"},{"upvote_count":"1","content":"The way I understand batch processing it has to either way for an event to occur or a condition to be met to be separated the batches of data. Example: End of the month credit card bill goes out.","poster":"Edgy_San","timestamp":"1707358860.0","comment_id":"1143979","comments":[{"poster":"Edgy_San","comment_id":"1143981","content":"*wait (Typo up there)","timestamp":"1707358920.0","upvote_count":"1"}]},{"content":"Selected Answer: C\nChoice D should not be correct because batch processing can process semi-structured (NoSQL) and even unstructured data (with complex and more effort) too.\n\nThe most logical answer is C, it's expected there will be a delay.","timestamp":"1698700920.0","upvote_count":"3","comment_id":"1058290","poster":"masadamsahid"},{"timestamp":"1698326160.0","comment_id":"1054603","poster":"james2033","content":"Selected Answer: C\nkeyword 'delay' for a batch.","upvote_count":"3"},{"timestamp":"1697182980.0","upvote_count":"1","poster":"jg_85","content":"Selected Answer: C\nThe fundamental requirement of such batch processing engines is to scale out computations to handle a large volume of data. Unlike real-time processing, batch processing is expected to have latencies","comment_id":"1042415"},{"upvote_count":"1","poster":"t201","comment_id":"1024212","content":"Answer is C","timestamp":"1696365120.0"},{"poster":"Yuezhen","content":"Selected Answer: C\nC should be the correct answer.","comment_id":"1014779","upvote_count":"2","timestamp":"1695461100.0"},{"upvote_count":"2","content":"Option C :\nhttps://learn.microsoft.com/en-us/azure/architecture/data-guide/technology-choices/batch-processing\nRead this para:\nThe fundamental requirement of such batch processing engines is to scale out computations to handle a large volume of data. Unlike real-time processing, batch processing is expected to have latencies (the time between data ingestion and computing a result) that measure in minutes to hours.","poster":"Ratz","comment_id":"1005316","timestamp":"1694485440.0"},{"content":"Selected Answer: C\nYes, it is possible to use batch processing with unstructured data. Batch processing is a data processing technique that involves collecting and processing data in predefined batches or groups. It can be used with both structured and unstructured data, although the approach and tools used may differ.","comment_id":"996377","upvote_count":"1","timestamp":"1693597140.0","poster":"lfparauj0"},{"comment_id":"996358","timestamp":"1693594020.0","upvote_count":"1","content":"Selected Answer: C\nC is correct","poster":"AZFabio"},{"poster":"batman1197","content":"Selected Answer: C\nCORRECT ANS IS C","upvote_count":"2","timestamp":"1691207760.0","comment_id":"972652"},{"content":"Option A is Stream Processing, NOT Batch Processing\nOption B - There is hard limits on data sizes for Batch processing, as they are meant to handle large amounts on data.\nOption C - Correct Answer.\nOption D - Batch Processing can be done Structure, Semi-Structured & Un-Structured data.","poster":"srgopalkr","upvote_count":"3","comment_id":"964408","timestamp":"1690437480.0","comments":[{"timestamp":"1690437660.0","comment_id":"964411","content":"Sorry for the Typo for Option B. Below, please find the corrected text.\nOption B - There ARE NO hard limits on data sizes for Batch processing, as they are meant to handle large amounts on data.","poster":"srgopalkr","upvote_count":"1"}]},{"poster":"HRKK","upvote_count":"1","comment_id":"939833","content":"CORRECT C","timestamp":"1688207160.0"},{"poster":"thuyoona","upvote_count":"1","comment_id":"934080","timestamp":"1687759200.0","content":"Selected Answer: C\nthe correct one must be C"},{"upvote_count":"1","comment_id":"930181","poster":"malute","content":"answer is c","timestamp":"1687412580.0"},{"content":"Selected Answer: C\naNSWER IS C","comment_id":"923267","upvote_count":"1","poster":"MALFOY77","timestamp":"1686750840.0"},{"poster":"Cristian_98","comment_id":"922121","upvote_count":"1","content":"Selected Answer: C\nIn my opinion, correct answer is C.","timestamp":"1686649500.0"},{"upvote_count":"1","poster":"Katliii_07","comment_id":"917430","timestamp":"1686157500.0","content":"Selected Answer: C\nC is the answer"},{"upvote_count":"2","comment_id":"899253","timestamp":"1684245060.0","poster":"chematab","content":"Selected Answer: C\nCorrect is C"},{"comment_id":"873596","content":"Selected Answer: C\nbatch processing can process both structured and unstructured data.","upvote_count":"2","timestamp":"1681820940.0","poster":"dax"},{"comment_id":"873213","poster":"Vanessa23","timestamp":"1681779000.0","content":"C - time delay for batch processing","upvote_count":"2"},{"comment_id":"868190","upvote_count":"16","timestamp":"1681295940.0","comments":[{"timestamp":"1681714800.0","poster":"Faizan96","comment_id":"872429","content":"100% ? Are you serious?","upvote_count":"2"}],"content":"I took the exam 12.04.2023 and got 1000, 100% score; this question appeared, correct answer:\nthere is a noticeable time delay between ingesting data and obtaining the data processing results","poster":"mamahani"},{"timestamp":"1680490080.0","upvote_count":"1","poster":"TestTurtle468","content":"I stand corrected. The reference isn't listed. Now I'm really curious! :)","comment_id":"859508"},{"comment_id":"859506","upvote_count":"2","content":"Hello. About every comment for this question stated that \"C\" is the answer (which I agree as well), but just curious if anyone has asked the question: Why is \"D\" the right answer? The reference is listed, but there's gotta be some method to this madness. :) Peace to all of you, especially the one's that are losing their minds on this question. :)","poster":"TestTurtle468","timestamp":"1680490020.0"},{"content":"Selected Answer: C\nShould be C, latency is expected.","upvote_count":"1","poster":"HC_Harms","timestamp":"1679679600.0","comment_id":"849503"},{"poster":"samjoon","timestamp":"1679415360.0","upvote_count":"1","comment_id":"846150","content":"Selected Answer: C\nsurely C"},{"poster":"AdrienBnhm","timestamp":"1679063340.0","upvote_count":"1","comment_id":"842064","content":"Definitely answer C"},{"timestamp":"1678707960.0","upvote_count":"1","poster":"dinith95","comment_id":"837894","content":"answer should be C"},{"poster":"Sacramento","content":"Latency is expected C","comment_id":"835835","timestamp":"1678530960.0","upvote_count":"1"},{"comment_id":"828568","content":"Selected Answer: C\nC is Correct Answer","upvote_count":"2","poster":"chiiiweiii","timestamp":"1677898980.0"},{"timestamp":"1677794280.0","content":"C. There is a noticeable time delay between ingesting data and obtaining the data processing results.","comment_id":"827479","upvote_count":"2","poster":"farisahmed80"},{"poster":"JorgeCastanho","content":"Selected Answer: C\ni think it is C","upvote_count":"1","comment_id":"824994","timestamp":"1677599880.0"},{"content":"Correct answer should be C:\nOne example of batch processing is transforming a large set of flat, semi-structured CSV or JSON files into a schematized and structured format that is ready for further querying.\nReference Microsoft Website:\nhttps://learn.microsoft.com/en-us/azure/architecture/data-guide/big-data/batch-","upvote_count":"3","poster":"salihGamar","comment_id":"823126","timestamp":"1677466500.0"},{"poster":"Traineeveneficus","timestamp":"1676973000.0","upvote_count":"1","comment_id":"816417","content":"Selected Answer: C\nThe answer is C"},{"comment_id":"813231","content":"Selected Answer: C\nBatch processing collects and stores data for later processing.","upvote_count":"1","timestamp":"1676735280.0","poster":"Joanna0"},{"content":"Selected Answer: C\nThere is a noticeable time delay between ingesting data and obtaining the data processing results.","timestamp":"1676621340.0","poster":"Hari46","upvote_count":"1","comment_id":"811626"},{"poster":"azurePL","comment_id":"808810","upvote_count":"1","content":"near 1y passed and the answer is still wrong indicated....","timestamp":"1676406300.0"},{"timestamp":"1675872180.0","content":"Selected Answer: C\nThere is a noticeable time delay between ingesting data and obtaining the data processing results.","upvote_count":"2","comment_id":"802211","poster":"ravick4u"},{"poster":"fernandostahelin","content":"Selected Answer: C\nAnswer should be C","timestamp":"1674663900.0","upvote_count":"1","comment_id":"787889"},{"comment_id":"787550","timestamp":"1674645960.0","content":"Selected Answer: C\nThe answer is C","poster":"Mohitsain","upvote_count":"1"},{"comment_id":"787365","upvote_count":"1","poster":"tuskostan","timestamp":"1674632580.0","content":"Selected Answer: C\nCorrect answer is C"},{"upvote_count":"1","comment_id":"786283","poster":"Pinha","timestamp":"1674546840.0","content":"C. Batch processing can process both structured and unstructured data."},{"comment_id":"785222","poster":"UA07","timestamp":"1674469740.0","upvote_count":"1","content":"Selected Answer: C\nCorrect answer should be C"},{"poster":"hsfbsfbdhsdfbdsjf","comment_id":"783089","timestamp":"1674286020.0","upvote_count":"1","content":"Selected Answer: C\nC. ANSWER"},{"upvote_count":"1","timestamp":"1674129900.0","poster":"vibhor2023","comment_id":"781091","content":"Selected Answer: C\nC is the answer"},{"upvote_count":"1","timestamp":"1673536380.0","comment_id":"773625","content":"Selected Answer: C\nIts C.","poster":"thakurvi"},{"upvote_count":"1","comment_id":"769737","poster":"J_ose","timestamp":"1673204400.0","content":"Correct answer: C"},{"timestamp":"1673091540.0","upvote_count":"1","content":"Selected Answer: C\nThe answer is C","poster":"sreekan2","comment_id":"768487"},{"upvote_count":"1","timestamp":"1673022300.0","poster":"PrinceOlaniyan","content":"Answer should be C","comment_id":"767885"},{"poster":"Moh_7akim","upvote_count":"1","comment_id":"761413","timestamp":"1672342200.0","content":"Selected Answer: C\nAnswer C"},{"timestamp":"1671666240.0","comment_id":"752874","content":"The Answer Should be 'C'","poster":"pathumfer","upvote_count":"1"},{"upvote_count":"1","timestamp":"1671449880.0","poster":"bebemo","comment_id":"749770","content":"Selected Answer: C\nthe answer should be C"},{"content":"Selected Answer: C\nthis should be C","upvote_count":"2","comment_id":"741650","poster":"bebemo","timestamp":"1670759880.0"},{"timestamp":"1669942320.0","content":"Selected Answer: C\nCorrect is C","upvote_count":"4","comment_id":"733273","poster":"nilsoncarlosf"},{"poster":"ale87e","content":"Selected Answer: C\nC es la correcta","comment_id":"730954","upvote_count":"1","timestamp":"1669768320.0"},{"timestamp":"1669106160.0","content":"The answer is D is Wrong \n because the Batch processing process structured and semi-structured data.\nand C is correct answer","upvote_count":"1","poster":"SAIVEENA","comment_id":"724178"},{"timestamp":"1669016640.0","content":"Selected Answer: D\nBatch processing can be used for unstructured data, therefore answer should be C","upvote_count":"1","comment_id":"723246","poster":"StickyCrusader"},{"content":"C because a, b, d are absolutely incorrect","poster":"Dusica","timestamp":"1669010640.0","comment_id":"723201","upvote_count":"1"},{"content":"Selected Answer: C\nYou can batch process structured or semi-structured data. You could batch process unstructured data too - but it's uncommon to do so.","poster":"TomGray1989","timestamp":"1667754480.0","comment_id":"712491","upvote_count":"2"},{"timestamp":"1667363460.0","poster":"AlbertKwan","upvote_count":"5","content":"So many wrong answers in Exam DP-900. ExamTopics is losing its credibility fast...","comment_id":"709617"},{"comment_id":"708203","upvote_count":"2","timestamp":"1667192160.0","content":"Selected Answer: C\nC is the correct answer","poster":"Tonnie85"},{"content":"Selected Answer: C\nAnswer should be C","poster":"MrTurbo","upvote_count":"1","comment_id":"707970","timestamp":"1667155260.0"},{"poster":"bittudon","upvote_count":"1","timestamp":"1666266720.0","comment_id":"699867","content":"Selected Answer: C\nCorrect answer is C"},{"poster":"raydel92","comment_id":"686408","timestamp":"1664911440.0","upvote_count":"1","content":"Selected Answer: C\nAlta latencia"},{"poster":"Nox1105","comment_id":"679474","timestamp":"1664174280.0","content":"Selected Answer: C\nC is correct","upvote_count":"1"},{"content":"Should be C.\n\"Pig. Pig is a declarative big data processing language used in many Hadoop distributions, including HDInsight. It is particularly useful for processing data that is unstructured or semi-structured.\"\nhttps://learn.microsoft.com/en-us/azure/architecture/data-guide/big-data/batch-processing","timestamp":"1663669560.0","poster":"Weewee123","upvote_count":"2","comment_id":"674031"},{"poster":"legoat233","comment_id":"667631","upvote_count":"1","content":"Answer is C.","timestamp":"1663041120.0"},{"poster":"Panny","comment_id":"664809","content":"Selected Answer: C\nC is correct","upvote_count":"1","timestamp":"1662741960.0"},{"comment_id":"660103","content":"definitely c","timestamp":"1662376740.0","upvote_count":"1","poster":"dannydanny168"},{"upvote_count":"1","poster":"Rajendraprasad","content":"Selected Answer: C\nCorrect :C","timestamp":"1661585940.0","comment_id":"652501"},{"upvote_count":"1","comment_id":"647775","content":"Correct : C","timestamp":"1660671720.0","poster":"FabianBigData"},{"poster":"DanielPessoa","content":"Selected Answer: C\nThe answer is C","timestamp":"1660152420.0","comment_id":"645080","upvote_count":"1"},{"poster":"MeerKatZA","comment_id":"644054","content":"Selected Answer: C\nDifferent wording to explain the expectation of High latency.","upvote_count":"2","timestamp":"1659952740.0"},{"upvote_count":"1","poster":"ottoman1453","timestamp":"1659650820.0","content":"answer should be C","comment_id":"642638"},{"content":"Selected Answer: C\nThe answer is C","timestamp":"1659006900.0","comment_id":"638655","upvote_count":"1","poster":"Tarek_74"},{"timestamp":"1658897820.0","content":"Selected Answer: C\nAbsolutely makes no sense that batch processing can only process strucutred data! How does (big) unstructured data get processed into structured in the first place?! It is *BATCH*","comment_id":"637806","poster":"fross","upvote_count":"4"},{"poster":"TapZxK","timestamp":"1658742240.0","content":"Selected Answer: C\nC is Correct","upvote_count":"1","comment_id":"636606"},{"upvote_count":"4","comment_id":"634175","content":"The Website gets the answers wrong ... on the test will they mark C correct or the stuff that this website supplies ?","timestamp":"1658340060.0","poster":"Rebirth100101"},{"poster":"D3COD3R","timestamp":"1658138820.0","content":"Selected Answer: C\nC is the correct answer","comment_id":"632961","upvote_count":"1"},{"upvote_count":"1","comment_id":"631156","timestamp":"1657772280.0","content":"Selected Answer: C\nc for sure","poster":"hunno_basha"},{"poster":"Marckos","comment_id":"630448","upvote_count":"1","timestamp":"1657620420.0","content":"Selected Answer: C\nThe answer is C"},{"comment_id":"630274","content":"Answer is C - There is a delay between ingestion and output because the batch has to be full for the processing to start. Batching is perfectly capable of handling any sort of data, including unstructured data that is usually sent as streams","timestamp":"1657597740.0","poster":"xRiot007","upvote_count":"3"},{"upvote_count":"1","comment_id":"626071","poster":"Eltooth","content":"Selected Answer: C\nC is the correct answer.","timestamp":"1656753600.0"},{"upvote_count":"2","content":"Selected Answer: C\nAnswer is C","timestamp":"1655950620.0","comment_id":"620721","poster":"SameerL"},{"poster":"chuchusmote","timestamp":"1655902620.0","content":"Selected Answer: C\nAnswer is C","comment_id":"620437","upvote_count":"1"},{"content":"The answer is C. One can batch process on structured, semi-structured, and non-structured data.","timestamp":"1655752380.0","comment_id":"619439","poster":"Jhall","upvote_count":"3"},{"content":"Selected Answer: C\nC is correct.","timestamp":"1655748900.0","comment_id":"619425","upvote_count":"1","poster":"WWDITDA"},{"poster":"Ishachohan","comment_id":"619282","upvote_count":"1","content":"Answer should be C","timestamp":"1655729280.0"},{"comment_id":"619066","upvote_count":"1","poster":"Deliboi","timestamp":"1655709360.0","content":"ans is C"},{"poster":"RicSpd","comment_id":"617576","content":"Selected Answer: C\nBatch processing can be performed on non-structured data too, so answer should be C","timestamp":"1655449140.0","upvote_count":"2"},{"upvote_count":"2","poster":"Rahulanwar","comment_id":"616451","content":"Selected Answer: C\nThe answer should be C","timestamp":"1655252580.0"},{"comment_id":"613231","poster":"Mern","content":"Selected Answer: C\nIt should be C","timestamp":"1654689300.0","upvote_count":"2"},{"comment_id":"612654","poster":"tejaskumar1234324","upvote_count":"2","content":"WRONG ANSWER AGAIN. IT SHOULD BE C","timestamp":"1654592640.0"},{"comment_id":"610545","content":"Selected Answer: C\nnothing to add, correct answer is C","timestamp":"1654165140.0","poster":"karlkruse2","upvote_count":"2"},{"timestamp":"1654138140.0","upvote_count":"2","content":"C is the answer","comment_id":"610420","poster":"Sayyunus2017"},{"timestamp":"1653703080.0","content":"Selected Answer: C\nCSV is semi-structured, but can be processed in Batch","poster":"wendymmmm","upvote_count":"2","comment_id":"608227"},{"comment_id":"607537","timestamp":"1653553500.0","upvote_count":"2","poster":"Ayor","content":"Selected Answer: C\nShould be C"},{"upvote_count":"3","comment_id":"603246","timestamp":"1652872080.0","poster":"dk87","content":"Exam: 05/18/2022"},{"poster":"EXODUS33","content":"Selected Answer: C\nBatch processing has latency when output records are generated","comment_id":"601886","timestamp":"1652585820.0","upvote_count":"1"},{"comment_id":"598764","content":"Selected Answer: C\nShould be C","upvote_count":"2","poster":"Learningboi","timestamp":"1652053080.0"},{"content":"C I SCORRECT","upvote_count":"1","comment_id":"598682","poster":"Ashishsingh07","timestamp":"1652038200.0"},{"poster":"sortie","timestamp":"1651816260.0","comment_id":"597573","content":"Selected Answer: C\nAnswer is C","upvote_count":"1"},{"comment_id":"595145","poster":"alonso3","timestamp":"1651334760.0","upvote_count":"2","content":"Selected Answer: C\nAnswer is C"},{"comment_id":"592353","poster":"bfan95","timestamp":"1650972540.0","upvote_count":"2","content":"Selected Answer: C\nAnswer: C"},{"poster":"cp2323","upvote_count":"3","comment_id":"590445","content":"Selected Answer: C\nanswer should be C","timestamp":"1650696480.0"},{"poster":"pads98","comment_id":"589602","content":"Selected Answer: C\nAnswer is C according to documentation - Unlike real-time processing, batch processing is expected to have latencies (the time between data ingestion and computing a result) that measure in minutes to hours.\n\nhttps://docs.microsoft.com/en-us/azure/architecture/data-guide/technology-choices/batch-processing","timestamp":"1650570720.0","upvote_count":"5"},{"poster":"ialberto","comments":[{"content":"https://docs.microsoft.com/en-us/azure/architecture/data-guide/big-data/batch-processing","comment_id":"589392","timestamp":"1650545700.0","poster":"ialberto","upvote_count":"1"}],"upvote_count":"2","comment_id":"589388","timestamp":"1650545520.0","content":"Correct Answer: C"},{"comment_id":"589119","poster":"DaveTTFF","content":"Selected Answer: C\nBatch processing expects a delay else it'd be real time.","timestamp":"1650520080.0","upvote_count":"3"}],"question_images":[],"answer_images":[],"answer_description":"","question_id":234,"answer_ET":"C","unix_timestamp":1650460260,"answers_community":["C (99%)","1%"],"isMC":true,"exam_id":73,"url":"https://www.examtopics.com/discussions/microsoft/view/73896-exam-dp-900-topic-1-question-47-discussion/","timestamp":"2022-04-20 15:11:00","answer":"C","choices":{"A":"The data ingested during batch processing must be processed as soon as the data is received.","B":"Large datasets must be split into batches of less than 1 GB before the data can be processed.","D":"Batch processing can only process data that is structured.","C":"There is a noticeable time delay between ingesting data and obtaining the data processing results."},"question_text":"What is a characteristic of batch processing?","topic":"1"},{"id":"DYe7cHRBe0DIYk1M1mYS","unix_timestamp":1650570900,"answer_description":"An aggregate function performs a calculation on a set of values, and returns a single value. The following are aggregate functions:\n✑ APPROX_COUNT_DISTINCT\n✑ AVG\n✑ CHECKSUM_AGG\n✑ COUNT\n✑ COUNT_BIG\n\nGROUPING -\n\n✑ GROUPING_ID\n✑ MAX\n✑ MIN\n✑ STDEV\n✑ STDEVP\n✑ STRING_AGG\n✑ SUM\n✑ VAR\n✑ VARP\nReference:\nhttps://docs.microsoft.com/en-us/sql/t-sql/functions/aggregate-functions-transact-sql?view=sql-server-ver15","url":"https://www.examtopics.com/discussions/microsoft/view/74063-exam-dp-900-topic-1-question-48-discussion/","exam_id":73,"question_images":["https://www.examtopics.com/assets/media/exam-media/04277/0006400001.png"],"answer_ET":"","answer":"","question_id":235,"timestamp":"2022-04-21 21:55:00","question_text":"HOTSPOT -\nSelect the answer that correctly completes the sentence.\nHot Area:\n//IMG//","isMC":false,"answers_community":[],"topic":"1","answer_images":["https://www.examtopics.com/assets/media/exam-media/04277/0006400002.png","https://www.examtopics.com/assets/media/exam-media/04277/0006400008.png"],"discussion":[{"timestamp":"1672658460.0","comment_id":"626072","poster":"Eltooth","content":"Max and Min","upvote_count":"19"},{"poster":"mamahani","timestamp":"1697107200.0","content":"I took the exam 12.04.2023 and got 1000, 100% score; this question appeared, correct answer:\nMAX and MIN","upvote_count":"15","comment_id":"868193"},{"timestamp":"1739436780.0","upvote_count":"1","comment_id":"1356027","poster":"Swamy90572","content":"Max and Min"},{"upvote_count":"1","timestamp":"1737007500.0","comment_id":"1341460","poster":"man5484","content":"Max and Min are examples of aggregate functions in SQL. They are used to calculate the maximum and minimum values of a column, respectively. Aggregate functions perform a calculation on a set of values and return a single result."},{"upvote_count":"2","timestamp":"1727685120.0","poster":"heobanten04","content":"I took the exam on 30.03.2024 and got 936; this question appeared, correct answer: MAX and MIN","comment_id":"1186037"},{"timestamp":"1724929080.0","poster":"AGTraining","content":"max and min","comment_id":"1162550","upvote_count":"1"},{"upvote_count":"1","timestamp":"1714137420.0","comment_id":"1054605","poster":"james2033","content":"MAX and MIN are aggregate functions."},{"comment_id":"828569","upvote_count":"3","poster":"chiiiweiii","content":"Correct Answer","timestamp":"1693789440.0"},{"timestamp":"1690157040.0","poster":"YOGESHGP19111982","upvote_count":"1","content":"MIN MAZ","comment_id":"786061"},{"timestamp":"1684053240.0","upvote_count":"1","comment_id":"717896","poster":"Abains","content":"Correct"},{"timestamp":"1668776880.0","comment_id":"603247","poster":"dk87","content":"Exam: 05/18/2022","upvote_count":"5"},{"upvote_count":"3","comment_id":"598684","poster":"Ashishsingh07","content":"MIN MAX","timestamp":"1667943060.0"},{"content":"correct","comment_id":"592354","upvote_count":"4","timestamp":"1666783740.0","poster":"bfan95"},{"content":"answer is correct.","comment_id":"590966","timestamp":"1666604280.0","poster":"arif17","upvote_count":"3"},{"content":"answer is correct.","timestamp":"1666382100.0","comment_id":"589603","poster":"pads98","upvote_count":"4"}]}],"exam":{"name":"DP-900","isBeta":false,"id":73,"lastUpdated":"12 Apr 2025","isMCOnly":false,"isImplemented":true,"provider":"Microsoft","numberOfQuestions":290},"currentPage":47},"__N_SSP":true}